{
    "items": [
        {
            "project_id": 300000130111136,
            "task_id": 100000219243656,
            "task_number": "2.2",
            "task_name": "Custom Help Screens"
        },
        {
            "project_id": 300000130111136,
            "task_id": 100000219243645,
            "task_number": "1.0",
            "task_name": "Documentation"
        },
        {
            "project_id": 300000130111136,
            "task_id": 100000219243657,
            "task_number": "2.1",
            "task_name": "On-Line Training Videos"
        },
        {
            "project_id": 300000130111136,
            "task_id": 100000219243646,
            "task_number": "3.0",
            "task_name": "Project Management"
        },
        {
            "project_id": 300000130111136,
            "task_id": 100000219243655,
            "task_number": "2.3",
            "task_name": "Proofing and QA Project"
        },
        {
            "project_id": 300000130111136,
            "task_id": 100000219243650,
            "task_number": "2.0",
            "task_name": "User On-Line Help"
        }
    ],
    "hasMore": false,
    "limit": 25,
    "offset": 0,
    "count": 6,
    "links": [
        {
            "rel": "self",
            "href": "http://129.158.228.138:8080/ords/timerite/timerite/CrewTimeProjectTaskPWA?project_id=300000130111136"
        },
        {
            "rel": "describedby",
            "href": "http://129.158.228.138:8080/ords/timerite/metadata-catalog/timerite/item"
        },
        {
            "rel": "first",
            "href": "http://129.158.228.138:8080/ords/timerite/timerite/CrewTimeProjectTaskPWA?project_id=300000130111136"
        }
    ]
}